README.md
setup.py
gnnuers/__init__.py
gnnuers/explain.py
gnnuers/get_datasets_stats.py
gnnuers/main.py
gnnuers/plot_full_comparison.py
gnnuers.egg-info/PKG-INFO
gnnuers.egg-info/SOURCES.txt
gnnuers.egg-info/dependency_links.txt
gnnuers.egg-info/not-zip-safe
gnnuers.egg-info/requires.txt
gnnuers.egg-info/top_level.txt
gnnuers/data/__init__.py
gnnuers/data/continuous_age_to_age_ranges.py
gnnuers/data/dataset.py
gnnuers/data/interaction.py
gnnuers/data/map_multi2binary.py
gnnuers/data/perturbed_dataset.py
gnnuers/data/preprocess_dataset.py
gnnuers/data/preprocess_lastfm2b.py
gnnuers/data/utils.py
gnnuers/evaluation/__init__.py
gnnuers/evaluation/eval.py
gnnuers/evaluation/graph_eval.py
gnnuers/explainers/__init__.py
gnnuers/explainers/bab.py
gnnuers/explainers/base.py
gnnuers/explainers/dpbg.py
gnnuers/explainers/metrics.py
gnnuers/explainers/utils.py
gnnuers/losses/__init__.py
gnnuers/losses/beyondacc_losses.py
gnnuers/losses/ranking_losses.py
gnnuers/models/__init__.py
gnnuers/models/gcmcperturbed.py
gnnuers/models/lightgcnperturbed.py
gnnuers/models/ngcf.py
gnnuers/models/ngcfperturbed.py
gnnuers/models/perturbed_model.py
gnnuers/models/utils.py
gnnuers/utils/__init__.py
gnnuers/utils/early_stopping.py
gnnuers/utils/plot_utils.py
gnnuers/utils/utils.py