Metadata-Version: 2.1
Name: gnnuers
Version: 0.0.6
Summary: A library to generate explanations of recommendations generated by GNNs.
Home-page: https://github.com/jackmedda/RS-BGExplainer
Author: jackmedda
Author-email: jackm.medda@gmail.com
License: UNKNOWN
Platform: UNKNOWN
Classifier: Development Status :: 3 - Alpha
Classifier: Environment :: GPU :: NVIDIA CUDA
Classifier: License :: OSI Approved :: GNU General Public License v3 (GPLv3)
